{
  "делать": ["выполнять", "осуществлять", "производить", "созидать"],
  "хороший": ["отличный", "прекрасный", "положительный", "достойный"],
  "быстрый": ["скорый", "оперативный", "стремительный"],
  "говорить": ["сообщать", "излагать", "вещать", "утверждать"],
  "важный": ["значимый", "существенный", "первостепенный"],
  "проблема": ["трудность", "задача", "препятствие"],
  "использовать": ["применять", "эксплуатировать", "задействовать"],
  "результат": ["итог", "показатель", "плод"],
  "работать": ["трудиться", "функционировать"],
  "статья": ["публикация", "материал"]
}
